trefleapi/__init__.py
trefleapi/api_operations.py
trefleapi/custom_validators.py
trefleapi/exceptions.py
trefleapi/main.py
trefleapi/models.py
trefleapi/queryset.py
trefleapi/rest_adapter.py
trefleapi/settings.py
trefleapi/utils.py
trefleapi-0.1.0.dist-info/LICENSE
trefleapi-0.1.0.dist-info/METADATA
trefleapi-0.1.0.dist-info/WHEEL
trefleapi-0.1.0.dist-info/top_level.txt
trefleapi-0.1.0.dist-info/RECORD
