Metadata-Version: 2.1
Name: trefleapi
Version: 0.1.0
Summary: A simple wrapper for the trefle botanical RESTAPI
Home-page: https://github.com/overlrd/trefle
Author: Overlrd
Author-email: sudooverloord@gmail.com
License: MIT
Project-URL: Bug Reports, https://github.com/oberlrd/trefle/issues
Project-URL: Source, https://github.com/oberlrd/trefle/
Keywords: trefle,botanical,plants,api
Classifier: Development Status :: 3 - Alpha
Classifier: Intended Audience :: Developers
Classifier: Topic :: Software Development :: Libraries
Classifier: License :: OSI Approved :: MIT License
Classifier: Programming Language :: Python :: 3.8
Classifier: Programming Language :: Python :: 3.9
Classifier: Programming Language :: Python :: 3.10
Requires-Python: >=3.10
License-File: LICENSE
Requires-Dist: requests (>=2.3)
Requires-Dist: appdirs (>=1.4.4)
Provides-Extra: dev
Requires-Dist: pytest ; extra == 'dev'
Requires-Dist: validators ; extra == 'dev'
Requires-Dist: twine (>=4.0.2) ; extra == 'dev'
